{
  "name": {
    "color": "#D30000",
    "translate": "trophy.trofers.composed",
    "with": [
      {
        "translate": "entity.pokecube.frosmoth"
      }
    ]
  },
  "effects": {
    "sound": {
      "soundEvent": "pokecube_mobs:mobs.frosmoth"
    },
    "rewards": {
      "lootTable": "pokecube:entities/snowball",
      "cooldown": 9600
    }
  },
  "display": {
    "offset": {
      "y": 0.5
    },
    "scale": 0.3846154
  },
  "entity": {
    "type": "pokecube:frosmoth",
    "nbt": "{OnGround: 0b}",
    "animated": true
  },
  "colors": {
    "base": "#606060",
    "accent": "#D30000"
  }
}