{
  "name": {
    "color": "#D30000",
    "translate": "trophy.trofers.composed",
    "with": [
      {
        "translate": "entity.pokecube.vibrava"
      }
    ]
  },
  "effects": {
    "sound": {
      "soundEvent": "pokecube_mobs:mobs.vibrava"
    },
    "rewards": {
      "lootTable": "pokecube:entities/sand_2",
      "cooldown": 9600
    }
  },
  "display": {
    "scale": 0.45454544
  },
  "entity": {
    "type": "pokecube:vibrava"
  },
  "colors": {
    "base": "#606060",
    "accent": "#D30000"
  }
}