{
  "replace": false,
  "values": [
    { "id": "betternether:anchor_tree_plate", "required": false },
    { "id": "betternether:mushroom_fir_plate", "required": false },
    { "id": "betternether:mushroom_plate", "required": false },
    { "id": "betternether:nether_sakura_plate", "required": false },
    { "id": "betternether:reeds_plate", "required": false },
    { "id": "betternether:rubeus_plate", "required": false },
    { "id": "betternether:stalagnate_planks_plate", "required": false },
    { "id": "betternether:wart_plate", "required": false },
    { "id": "betternether:willow_plate", "required": false }
  ]
}